README.md
setup.cfg
setup.py
rocketbot/__init__.py
rocketbot/client.py
rocketbot/exception.py
rocketbot/master.py
rocketbot/py.typed
rocketbot.egg-info/PKG-INFO
rocketbot.egg-info/SOURCES.txt
rocketbot.egg-info/dependency_links.txt
rocketbot.egg-info/requires.txt
rocketbot.egg-info/top_level.txt
rocketbot/bots/__init__.py
rocketbot/bots/accesscontrol.py
rocketbot/bots/base.py
rocketbot/bots/messagefilter.py
rocketbot/bots/messagehandler.py
rocketbot/commands/__init__.py
rocketbot/commands/base.py
rocketbot/commands/catchall.py
rocketbot/commands/ping.py
rocketbot/commands/poll.py
rocketbot/commands/usage.py
rocketbot/models/__init__.py
rocketbot/models/apiobjects.py
rocketbot/models/clientresults.py
rocketbot/models/enums.py
rocketbot/models/rcdatetime.py
rocketbot/utils/__init__.py
rocketbot/utils/poll.py
rocketbot/utils/sentry.py
rocketbot/utils/usage.py