Metadata-Version: 1.2
Name: rocketbot
Version: 0.2.3
Summary: A RocketChat bot-framework with a DDP- and a Rest-Client
Home-page: https://github.com/corewire/rocketbot
Author: Stefan Möhrle
Author-email: stefan@corewire.de
License: MIT
Keywords: rocketchat,ddp-client,restclient,bot-framework
Platform: UNKNOWN
Classifier: Development Status :: 4 - Beta
Classifier: Intended Audience :: Developers
Classifier: Topic :: Software Development :: Libraries :: Application Frameworks
Classifier: License :: OSI Approved :: MIT License
Requires-Python: >=3.7
